{
    "defaultSeverity": "error",
    "extends": [
        "tslint:recommended"
    ],
    "jsRules": {},
    "rules": {
        "arrow-parens": [false],
        "max-line-length": [false],
        "quotemark": [false],
        "no-trailing-whitespace": [false],
        "no-console": [false],
        "no-string-literal": [false],
        "ordered-imports": [false],
        "array-type": [true, "generic"],
        "no-angle-bracket-type-assertion": [false],
        "max-classes-per-file": [false],
        "curly": [false],
        "object-literal-sort-keys": [false],
        "variable-name": [false],
        "no-bitwise": [false],
        "no-conditional-assignment": [false],
        "no-namespace": [false],
        "whitespace": [false],
        "no-shadowed-variable": [false],
        "no-eval": [false]
    },
    "rulesDirectory": []
}
